phem_distributions/Binomialdistribution.py
phem_distributions/Gaussiandistribution.py
phem_distributions/Generaldistribution.py
phem_distributions/__init__.py
phem_distributions-0.1.dist-info/METADATA
phem_distributions-0.1.dist-info/WHEEL
phem_distributions-0.1.dist-info/top_level.txt
phem_distributions-0.1.dist-info/RECORD
