Metadata-Version: 2.1
Name: phem-distributions
Version: 0.1
Summary: Gaussian and Binomial distributions
Home-page: UNKNOWN
Author: Tindi
Author-email: myemail@donphemull.com
License: UNKNOWN
Platform: UNKNOWN
